ultrabench/__about__.py
ultrabench/__init__.py
ultrabench/__main__.py
ultrabench/cli.py
ultrabench/datasets/__init__.py
ultrabench/datasets/aul.py
ultrabench/datasets/butterfly.py
ultrabench/datasets/camus.py
ultrabench/datasets/fatty_liver.py
ultrabench/datasets/gbcu.py
ultrabench/datasets/mmotu.py
ultrabench/datasets/open_kidney.py
ultrabench/datasets/pocus.py
ultrabench/datasets/psfhs.py
ultrabench/datasets/stanford_thyroid.py
ultrabench/datasets/utils.py
ultrabench-1.0.0.dist-info/METADATA
ultrabench-1.0.0.dist-info/WHEEL
ultrabench-1.0.0.dist-info/entry_points.txt
ultrabench-1.0.0.dist-info/licenses/LICENSE
ultrabench-1.0.0.dist-info/RECORD
