Metadata-Version: 2.4
Name: ultrabench
Version: 1.0.0
Summary: A standardized benchmark of ultrasound image analysis tasks.
Project-URL: Homepage, https://github.com/adamtupper/ultrabench
Project-URL: Documentation, https://github.com/adamtupper/ultrabench/wiki
Project-URL: Issues, https://github.com/adamtupper/ultrabench/issues
Author-email: Adam Tupper <adam.tupper.1@ulaval.ca>
License-Expression: MIT
License-File: LICENSE
Classifier: Operating System :: OS Independent
Classifier: Programming Language :: Python :: 3
Requires-Python: >=3.8
Requires-Dist: h5py>=3.11.0
Requires-Dist: imageio[ffmpeg]>=0.5.1
Requires-Dist: nibabel>=5.2.1
Requires-Dist: numpy>=1.26.4
Requires-Dist: opencv-python>=4.10.0.84
Requires-Dist: pandas>=2.2.1
Requires-Dist: scikit-image>=0.24.0
Requires-Dist: scikit-learn>=1.5.0
Requires-Dist: simpleitk>=2.3.1
Requires-Dist: typer>=0.15.1
Provides-Extra: dev
Requires-Dist: nbstripout>=0.8.1; extra == 'dev'
Requires-Dist: pre-commit>=4.0.1; extra == 'dev'
Requires-Dist: ruff>=0.8.4; extra == 'dev'
